bihexbase/__init__.py
bihexbase/bihex.py
bihex_domedi-0.0.6.dist-info/LICENSE
bihex_domedi-0.0.6.dist-info/METADATA
bihex_domedi-0.0.6.dist-info/WHEEL
bihex_domedi-0.0.6.dist-info/top_level.txt
bihex_domedi-0.0.6.dist-info/RECORD
