Metadata-Version: 2.1
Name: bihex-domedi
Version: 0.0.6
Summary: Convert to and from multiple bases
Home-page: https://github.com/EduardAlex/BiHex
Author: David Eduard
Author-email: edyalex.david@gmail.com
License: UNKNOWN
Platform: UNKNOWN
Classifier: Programming Language :: Python :: 3
Classifier: License :: OSI Approved :: MIT License
Classifier: Operating System :: OS Independent
Requires-Python: >=3.6
